<?xml version="1.0" encoding="utf-8" ?>
<dwsync>
<file name="1-level-page.php" server="ftp.theharrington.com//" local="130386469200000000" remote="130386469200000000" />
<file name="2-level-page.php" server="ftp.theharrington.com//" local="130386469200000000" remote="130386469200000000" />
<file name="3-level-page-first.php" server="ftp.theharrington.com//" local="130437597600000000" remote="130437597600000000" />
<file name="3-level-page.php" server="ftp.theharrington.com//" local="130437601200000000" remote="130437601200000000" />
<file name="Properties-2-level-News-page.php.temp" server="ftp.theharrington.com//" local="130391663400000000" remote="130391663400000000" />
<file name="Properties-2-level-page.php" server="ftp.theharrington.com//" local="130390453200000000" remote="130390453200000000" />
<file name="Properties-3-level-contact-us-home-page.php" server="ftp.theharrington.com//" local="130427045400000000" remote="130427045400000000" />
<file name="Properties-3-level-contact-us-page.php" server="ftp.theharrington.com//" local="130426516200000000" remote="130426516200000000" />
<file name="Properties-3-level-page.php" server="ftp.theharrington.com//" local="130395136800000000" remote="130395136800000000" />
</dwsync>